{
    "0":["無"],
    "90001":["雙月",0,15,0,10,"速攻回力鏢","森之界",0,0],
    "90002":["銀葉",5,10,0,0,"小太刀","森之界",0,0],
    "90003":["雲衣",10,0,10,0,"保護型外衣","森之界",0,0],
    "90004":["絕影",0,30,-10,0,"黑色的攻擊型妖刀","森之界",0,0],
    "90005":["陽炎",5,1.1,0,0,"高碳鋼直刀","森之界",0,0],
    "90006":["赤界",10,30,-5,0,"黑色長刀","森之界",0,0],
    "40001":["春聯",20,20,5,5,"春到、福到、新年到","新年活動",0,0],
    "40002":["鞭炮",5,20,5,20,"似乎是用來驅趕年獸的...","新年活動",0,0],
    "40003":["紅包",20,5,20,5,"打開的話心情可能會180度大轉變喔...","新年活動",0,0],
    "90007":["充能護甲",10,0,25,0,"狟玉首席研究人員埃努斯博士回到地下實驗室後的第一份成品","埃努斯",0,0],
    "90008":["蜂巢",0,20,0,0,"遠距離霰彈發射器","埃努斯",0,0],
    "90009":["尖刺護甲",0,8,21,0,"護甲上的尖刺能反傷對手","埃努斯",0,0],
    "90010":["巨人化激素",21,30,-12,14,"能短暫巨人化的禁藥","埃努斯",0,0],
    "90011":["雷電裝甲",0,0,11,27,"外層包覆著電流的裝甲。此技術非比尋常，這似乎不是他的全部......","埃努斯",0,0],
    "90012":["雁翎",0,25,5,-10,"一把外型有如大雁翎毛的鋼刀","埃努斯",0,0],
    "90013":["御柳",0,25,-10,5,"一把極輕的長劍，刀刃很薄故得名","埃努斯",0,0],
    "90014":["罐頭麵包",20,0,0,10,"緊急糧食，味道比兵糧丸好多了","埃努斯",0,0],
    "90015":["EPI腎上腺素",45,15,-30,20,"急救用激素，恢復戰力用的興奮劑，會進入短暫的亢奮狀態","埃努斯",0,0],
    "90016":["ARP腎上腺素",-20,20,25,20,"可以強制進入短暫的狂暴狀態，但要小心心律不整的問題","埃努斯",0,0],
    "90017":["卡雷斯",-15,36,-10,24,"以\"魔晶金屬\"打造的半自動手槍","埃努斯",0,0],
    "90018":["格羅根",30,0,1.15,-25,"以狟玉技術\"護城盾\"為基礎，混入魔晶金屬的改造款","埃努斯",0,0],
    "90019":["厄瑞玻斯",-50,1.15,50,1.08,"將大量血液藉由魔晶的吸收反應充能機動裝甲，進而使戰力上升","埃努斯",0,0],
    "90020":["考爾比",0,0,1.15,1.15,"能遁形於黑暗之中的防禦型斗篷","埃努斯",0,0],
    "90021":["扎馬爾岡",21,13,14,-18,"結合魔晶金屬打造的秘咒項鍊","埃努斯",0,0],
    "20001":["南瓜燈",-5,50,-5,-5,"神秘的南瓜燈。技能：「召魂術」，開場時，有25%機率提升自身攻擊力100%，持續三回合。","萬聖節",1,100001],
    "20002":["吸血鬼披風",-5,-5,-5,50,"似乎有什麼秘密在...技能：「黑夜之王」，當對手成功閃避時，有25%機率降低對方速度50%，持續三回合。","萬聖節",2,200001],
    "20003":["木乃伊繃帶",50,-5,-5,-5,"空氣中瀰漫著福馬林的味道...技能：「金字塔的秘密」，當HP小於50時， 若速度至少有100，則有50%機率犧牲50點速度轉換成100點血量。","萬聖節",3,300001],
    "20004":["科學怪人的大腦",-5,-5,50,-5,"尋找科學怪人的大腦？技能：「在這裡！」，開場時，若敵方攻擊力大於自身防禦力，則有50%機率提升自身防禦力100%。","萬聖節",1,100002],
    "90022":["山吹",20,1.3,-10,-30,"一把黑色的大支開山刀","凜野",0,0],
    "90023":["豬又",0,15,1.2,-20,"豬皮製的保暖毛皮大衣","凜野",0,0],
    "90024":["雪柳",0,25,0,10,"一把輕量化的白色長劍","凜野",0,0],
    "90025":["飛羽",5,-10,10,1.5,"一雙即使是在雪地也能行走的神奇鞋","凜野",0,0],
    "90026":["汁紅",1.1,30,10,0,"一種極為珍貴的動物之血液，能有治癒的效果","凜野",0,0],
    "90027":["原雪",20,-10,1.5,-10,"一雙用上等毛皮製成的極保暖手套","凜野",0,0],
    "90028":["木蕪",0,20,0,15,"一根可以在沙漠區打野兔的木棒","凜野",0,0],
    "20005":["打虎棒",10,20,20,20,"技能：「調虎離山」，開場時，5%機率增加自身血量500%","虎年"],
    "20006":["刮刮樂",20,5,20,5,"技能：「如虎添翼」，開場時，提升自身攻擊力10%及速度15%","虎年"],
    "20007":["新衣",10,10,10,10,"技能：「狐假虎威」，開場時，自身除了等級外之所有數值會複製成對手數值，維持三回合","虎年"],
    "20008":["煙火",20,10,20,5,"技能：「虎頭蛇尾」，開場時，提升自身除了等級外之所有數值100%，維持一到三回合","虎年"]
}